Metadata-Version: 2.1
Name: Mensajes-rhawen
Version: 5
Summary: Un paquete para saludar y despedir
Home-page: https://cacafuti.wordpress.com
Author: Rhawen
Author-email: caca@sí.com
Classifier: Environment :: Console
Classifier: Intended Audience :: Developers
Classifier: License :: OSI Approved :: MIT License
Classifier: Operating System :: OS Independent
Classifier: Programming Language :: Python
Classifier: Programming Language :: Python :: 3.10
Classifier: Topic :: Utilities
License-File: LICENSE
Requires-Dist: numpy >1
